fosslight_scanner/__init__.py
fosslight_scanner/_get_input.py
fosslight_scanner/_help.py
fosslight_scanner/_parse_setting.py
fosslight_scanner/_run_compare.py
fosslight_scanner/cli.py
fosslight_scanner/common.py
fosslight_scanner/fosslight_scanner.py
fosslight_scanner/resources/bom_compare.html
fosslight_scanner-2.1.15.dist-info/licenses/LICENSE
fosslight_scanner-2.1.15.dist-info/METADATA
fosslight_scanner-2.1.15.dist-info/WHEEL
fosslight_scanner-2.1.15.dist-info/entry_points.txt
fosslight_scanner-2.1.15.dist-info/top_level.txt
fosslight_scanner-2.1.15.dist-info/RECORD
