Metadata-Version: 2.4
Name: fosslight_scanner
Version: 2.1.15
Summary: FOSSLight Scanner
Home-page: https://github.com/fosslight/fosslight_scanner
Download-URL: https://github.com/fosslight/fosslight_scanner
Author: LG Electronics
License: Apache-2.0
Classifier: License :: OSI Approved :: Apache Software License
Classifier: Programming Language :: Python :: 3
Classifier: Programming Language :: Python :: 3.10
Classifier: Programming Language :: Python :: 3.11
Classifier: Programming Language :: Python :: 3.12
Requires-Python: >=3.10,<3.13
License-File: LICENSE
Requires-Dist: future
Requires-Dist: pandas
Requires-Dist: openpyxl
Requires-Dist: progress
Requires-Dist: pyyaml
Requires-Dist: beautifulsoup4
Requires-Dist: fosslight_util<3.0.0,>=2.1.38
Requires-Dist: fosslight_source<3.0.0,>=2.2.3
Requires-Dist: fosslight_dependency<5.0.0,>=4.1.31
Requires-Dist: fosslight_binary<6.0.0,>=5.1.17
Requires-Dist: fosslight_prechecker<5.0.0,>=4.0.0
Dynamic: author
Dynamic: classifier
Dynamic: description
Dynamic: description-content-type
Dynamic: download-url
Dynamic: home-page
Dynamic: license
Dynamic: license-file
Dynamic: requires-dist
Dynamic: requires-python
Dynamic: summary
